woodwell_theme/__init__.py
woodwell_theme/colors/__init__.py
woodwell_theme/colors/colors.py
woodwell_theme/fonts/__init__.py
woodwell_theme/fonts/fonts.py
woodwell_theme/fonts/ttf/gemeli-mono-bold.ttf
woodwell_theme/fonts/ttf/gemeli-mono-regular.ttf
woodwell_theme/fonts/ttf/ginto-normal-bold.ttf
woodwell_theme/fonts/ttf/ginto-normal-medium.ttf
woodwell_theme/fonts/ttf/ginto-normal-regular.ttf
woodwell_theme/style/__init__.py
woodwell_theme/style/theme.mplstyle
woodwell_theme-0.1.0.dist-info/licenses/LICENSE
woodwell_theme-0.1.0.dist-info/METADATA
woodwell_theme-0.1.0.dist-info/WHEEL
woodwell_theme-0.1.0.dist-info/top_level.txt
woodwell_theme-0.1.0.dist-info/RECORD
