Metadata-Version: 2.4
Name: woodwell_theme
Version: 0.1.0
Summary: Reusable Matplotlib theme for Woodwell Climate Research Center
Author: jakidxav
License: MIT
Requires-Python: >=3.10
License-File: LICENSE
Requires-Dist: drawarrow
Requires-Dist: highlight_text
Requires-Dist: matplotlib
Requires-Dist: pyfonts
Requires-Dist: pypalettes
Provides-Extra: dev
Requires-Dist: build; extra == "dev"
Requires-Dist: flake8; extra == "dev"
Requires-Dist: setuptools; extra == "dev"
Requires-Dist: twine; extra == "dev"
Requires-Dist: wheel; extra == "dev"
Provides-Extra: demo
Requires-Dist: ipykernel; extra == "demo"
Requires-Dist: notebook; extra == "demo"
Requires-Dist: pandas; extra == "demo"
Requires-Dist: pillow<11,>=10.0; extra == "demo"
Dynamic: license-file
